{
  "api": {
    "vybustempapp2API": {
      "service": "AppSync",
      "providerPlugin": "awscloudformation",
      "dependsOn": [],
      "output": {
        "authConfig": {
          "defaultAuthentication": {
            "authenticationType": "API_KEY",
            "apiKeyConfig": {
              "apiKeyExpirationDays": 365,
              "apiKeyExpirationDate": "2023-06-28T18:41:56.356Z",
              "description": "our API key"
            }
          },
          "additionalAuthenticationProviders": []
        }
      }
    }
  }
}